setup.py
imhotep_eslint/__init__.py
imhotep_eslint/plugin.py
imhotep_eslint/plugin_test.py
imhotep_eslint.egg-info/PKG-INFO
imhotep_eslint.egg-info/SOURCES.txt
imhotep_eslint.egg-info/dependency_links.txt
imhotep_eslint.egg-info/entry_points.txt
imhotep_eslint.egg-info/pbr.json
imhotep_eslint.egg-info/requires.txt
imhotep_eslint.egg-info/top_level.txt