Metadata-Version: 1.0
Name: imhotep-eslint
Version: 0.0.1
Summary: An imhotep plugin for eslint
Home-page: https://github.com/justinabrahms/imhotep_eslint
Author: Justin Abrahms
Author-email: justin@abrah.ms
License: MIT
Platform: UNKNOWN
